LICENSE
MANIFEST.in
README.md
setup.cfg
setup.py
smolder
charcoal/__init__.py
charcoal/charcoal.py
charcoal/colours.py
charcoal/expect_status_code.py
charcoal/expect_status_code.yapsy-plugin
charcoal/get_host_overrides.py
charcoal/get_verify.py
charcoal/headers_present.py
charcoal/headers_present.yapsy-plugin
charcoal/ldap_attribute_value_equals.py
charcoal/ldap_attribute_value_equals.yapsy-plugin
charcoal/output.py
charcoal/response_body_contains.py
charcoal/response_body_contains.yapsy-plugin
charcoal/response_body_doesnt_contain.py
charcoal/response_body_doesnt_contain.yapsy-plugin
charcoal/response_header_value_contains.py
charcoal/response_header_value_contains.yapsy-plugin
charcoal/response_header_values.py
charcoal/response_header_values.yapsy-plugin
charcoal/response_json_contains.py
charcoal/response_json_contains.yapsy-plugin
charcoal/response_max_time_ms.py
charcoal/response_max_time_ms.yapsy-plugin
charcoal/response_redirect.py
charcoal/response_redirect.yapsy-plugin
charcoal/tcptest.py
charcoal/validate_json.py
charcoal/validate_json.yapsy-plugin
docs/contributing.md
docs/examples.md
docs/index.md
docs/inputs.md
docs/outcomes.md
docs/plugins.md
docs/tests.md
examples/aws_status.json
examples/example_test.json
examples/file_upload.json
examples/file_upload.yaml
examples/github_status.json
examples/github_status.yaml
examples/header_test.json
examples/soa_test.json
smolder.egg-info/PKG-INFO
smolder.egg-info/SOURCES.txt
smolder.egg-info/dependency_links.txt
smolder.egg-info/not-zip-safe
smolder.egg-info/requires.txt
smolder.egg-info/top_level.txt
tests/fixtures/badssl.yaml
tests/fixtures/big_test.json
tests/fixtures/github_status.json
tests/fixtures/harsh_github_status.json
tests/fixtures/invalid_yaml.yaml
tests/fixtures/tcp_test.yaml
tests/fixtures/tcp_test_local.yaml
tests/fixtures/tcp_test_local_fail.yaml
tests/fixtures/v1_github_status.yaml
tests/fixtures/validate_json.yaml
tests/mocks/validate_json_response.json
tests/mocks/validate_json_response_fail.json