Metadata-Version: 1.1
Name: smolder
Version: 0.6.0.0
Summary: Json wrapper around requests for simple smoke testing.
Home-page: http://sky-shiny.github.io/smolder/
Author: Max Cameron
Author-email: maxwell.cameron@johngaltsystems.com
License: BSD License
Platform: UNKNOWN
Requires: requests
Requires: httpretty
Requires: nose
Requires: jsonpickle
Requires: argh
Requires: decorator
Requires: dpath
Requires: ecdsa
Requires: Jinja2
Requires: MarkupSafe
Requires: requests
Requires: retry
Requires: retrying
Requires: six
Requires: jsonpickle
Requires: PyYAML
Requires: Yapsy
Requires: validictory
Requires: nose
Requires: httpretty
Requires: ldap3
